odoo9_addon_l10n_es_mis_report-9.0.1.0.0.99.dev8-py3.8-nspkg.pth
odoo_addons/l10n_es_mis_report/README.rst
odoo_addons/l10n_es_mis_report/__init__.py
odoo_addons/l10n_es_mis_report/__openerp__.py
odoo_addons/l10n_es_mis_report/data/mis_report_balance_abreviated.xml
odoo_addons/l10n_es_mis_report/data/mis_report_balance_normal.xml
odoo_addons/l10n_es_mis_report/data/mis_report_balance_sme.xml
odoo_addons/l10n_es_mis_report/data/mis_report_pyg_abreviated.xml
odoo_addons/l10n_es_mis_report/data/mis_report_pyg_normal.xml
odoo_addons/l10n_es_mis_report/data/mis_report_pyg_sme.xml
odoo_addons/l10n_es_mis_report/data/mis_report_revenues_expenses_normal.xml
odoo_addons/l10n_es_mis_report/data/mis_report_styles.xml
odoo_addons/l10n_es_mis_report/i18n/ca.po
odoo_addons/l10n_es_mis_report/i18n/l10n_es_mis_report.pot
odoo_addons/l10n_es_mis_report/static/description/icon.png
odoo9_addon_l10n_es_mis_report-9.0.1.0.0.99.dev8.dist-info/METADATA
odoo9_addon_l10n_es_mis_report-9.0.1.0.0.99.dev8.dist-info/WHEEL
odoo9_addon_l10n_es_mis_report-9.0.1.0.0.99.dev8.dist-info/namespace_packages.txt
odoo9_addon_l10n_es_mis_report-9.0.1.0.0.99.dev8.dist-info/top_level.txt
odoo9_addon_l10n_es_mis_report-9.0.1.0.0.99.dev8.dist-info/RECORD
