Metadata-Version: 2.1
Name: odoo9-addon-l10n-es-mis-report
Version: 9.0.1.0.0.99.dev8
Summary: Plantillas MIS Builder para informes contables españoles
Home-page: https://github.com/OCA/l10n-spain
Author: Eficent,Tecnativa,Odoo Community Association (OCA)
Author-email: support@odoo-community.org
License: AGPL-3
Platform: UNKNOWN
Classifier: Programming Language :: Python
Classifier: Framework :: Odoo
Classifier: Framework :: Odoo :: 9.0
Classifier: License :: OSI Approved :: GNU Affero General Public License v3
Requires-Python: ~=2.7
Requires-Dist: odoo9-addon-mis-builder
Requires-Dist: odoo (<9.1a,>=9.0a)
